{
 "system_name": "hyp1",
 "speakers": {
  "S05C007M2_2LG": {
   "(S05C007M2_2LG-words)": {
    "SystemName": "hyp1",
    "SpeakerID": "S05C007M2_2LG",
    "sentence_id": "(S05C007M2_2LG-words)",
    "sequence": 0,
    "word_count": 77,
    "words": [
     {
      "eval_label": "D",
      "ref": "water",
      "hyp": ""
     },
     {
      "eval_label": "D",
      "ref": "*",
      "hyp": ""
     },
     {
      "eval_label": "D",
      "ref": "mevrouw*(meervoud)",
      "hyp": ""
     },
     {
      "eval_label": "D",
      "ref": "*",
      "hyp": ""
     },
     {
      "eval_label": "D",
      "ref": "drogen*(drongen)",
      "hyp": ""
     },
     {
      "eval_label": "D",
      "ref": "winkel",
      "hyp": ""
     },
     {
      "eval_label": "D",
      "ref": "auto",
      "hyp": ""
     },
     {
      "eval_label": "D",
      "ref": "*s",
      "hyp": ""
     },
     {
      "eval_label": "D",
      "ref": "schouders*(schouder)",
      "hyp": ""
     },
     {
      "eval_label": "D",
      "ref": "verhaal",
      "hyp": ""
     },
     {
      "eval_label": "D",
      "ref": "koning",
      "hyp": ""
     },
     {
      "eval_label": "D",
      "ref": "*",
      "hyp": ""
     },
     {
      "eval_label": "D",
      "ref": "*s",
      "hyp": ""
     },
     {
      "eval_label": "D",
      "ref": "koning",
      "hyp": ""
     },
     {
      "eval_label": "D",
      "ref": "*s",
      "hyp": ""
     },
     {
      "eval_label": "D",
      "ref": "moeilijk",
      "hyp": ""
     },
     {
      "eval_label": "D",
      "ref": "*s",
      "hyp": ""
     },
     {
      "eval_label": "S",
      "ref": "speelplaats",
      "hyp": "war"
     },
     {
      "eval_label": "S",
      "ref": "*s",
      "hyp": "toch"
     },
     {
      "eval_label": "S",
      "ref": "drinken",
      "hyp": "meegevold"
     },
     {
      "eval_label": "S",
      "ref": "*s",
      "hyp": "tdroen"
     },
     {
      "eval_label": "S",
      "ref": "hoofdpijn",
      "hyp": "incl"
     },
     {
      "eval_label": "S",
      "ref": "regen",
      "hyp": "altel"
     },
     {
      "eval_label": "S",
      "ref": "vliegtuig",
      "hyp": "schoutoch"
     },
     {
      "eval_label": "S",
      "ref": "stoppen",
      "hyp": "verel"
     },
     {
      "eval_label": "S",
      "ref": "*",
      "hyp": "go"
     },
     {
      "eval_label": "S",
      "ref": "*",
      "hyp": "kn"
     },
     {
      "eval_label": "S",
      "ref": "*",
      "hyp": "moland"
     },
     {
      "eval_label": "S",
      "ref": "*",
      "hyp": "speelplaat"
     },
     {
      "eval_label": "S",
      "ref": "*",
      "hyp": "trent"
     },
     {
      "eval_label": "S",
      "ref": "*",
      "hyp": "en"
     },
     {
      "eval_label": "S",
      "ref": "*",
      "hyp": "hoofd"
     },
     {
      "eval_label": "S",
      "ref": "*",
      "hyp": "pin"
     },
     {
      "eval_label": "S",
      "ref": "*",
      "hyp": "pagen"
     },
     {
      "eval_label": "S",
      "ref": "stoppen",
      "hyp": "fniegtus"
     },
     {
      "eval_label": "S",
      "ref": "stoppen",
      "hyp": "stopen"
     },
     {
      "eval_label": "C",
      "ref": "opnieuw",
      "hyp": "opnieuw"
     },
     {
      "eval_label": "C",
      "ref": "gooien",
      "hyp": "gooien"
     },
     {
      "eval_label": "D",
      "ref": "*",
      "hyp": ""
     },
     {
      "eval_label": "C",
      "ref": "sneeuwen",
      "hyp": "sneeuwen"
     },
     {
      "eval_label": "C",
      "ref": "moeder",
      "hyp": "moeder"
     },
     {
      "eval_label": "D",
      "ref": "*",
      "hyp": ""
     },
     {
      "eval_label": "D",
      "ref": "*",
      "hyp": ""
     },
     {
      "eval_label": "S",
      "ref": "liedje",
      "hyp": "mote"
     },
     {
      "eval_label": "S",
      "ref": "*",
      "hyp": "g"
     },
     {
      "eval_label": "S",
      "ref": "potlood",
      "hyp": "sp"
     },
     {
      "eval_label": "S",
      "ref": "fietsbel",
      "hyp": "potsulots"
     },
     {
      "eval_label": "S",
      "ref": "vinger",
      "hyp": "fintel"
     },
     {
      "eval_label": "S",
      "ref": "dichtbij",
      "hyp": "vinnor"
     },
     {
      "eval_label": "S",
      "ref": "dichtbij",
      "hyp": "tegen"
     },
     {
      "eval_label": "S",
      "ref": "meisje",
      "hyp": "t"
     },
     {
      "eval_label": "S",
      "ref": "*",
      "hyp": "bi"
     },
     {
      "eval_label": "S",
      "ref": "*",
      "hyp": "e"
     },
     {
      "eval_label": "S",
      "ref": "chauffeur",
      "hyp": "schijfter"
     },
     {
      "eval_label": "C",
      "ref": "muziek",
      "hyp": "muziek"
     },
     {
      "eval_label": "C",
      "ref": "waarom",
      "hyp": "waarom"
     },
     {
      "eval_label": "D",
      "ref": "scheuren*(schuren)",
      "hyp": ""
     },
     {
      "eval_label": "D",
      "ref": "*",
      "hyp": ""
     },
     {
      "eval_label": "D",
      "ref": "lawaai",
      "hyp": ""
     },
     {
      "eval_label": "S",
      "ref": "*",
      "hyp": "um"
     },
     {
      "eval_label": "S",
      "ref": "zwemmen",
      "hyp": "law"
     },
     {
      "eval_label": "S",
      "ref": "vuurwerk",
      "hyp": "em"
     },
     {
      "eval_label": "S",
      "ref": "appel",
      "hyp": "r"
     },
     {
      "eval_label": "S",
      "ref": "*(spellen)",
      "hyp": "wark"
     },
     {
      "eval_label": "S",
      "ref": "cola",
      "hyp": "s"
     },
     {
      "eval_label": "S",
      "ref": "kussen",
      "hyp": "s"
     },
     {
      "eval_label": "S",
      "ref": "eerste",
      "hyp": "e"
     },
     {
      "eval_label": "S",
      "ref": "circus",
      "hyp": "scho"
     },
     {
      "eval_label": "S",
      "ref": "*",
      "hyp": "tisem"
     },
     {
      "eval_label": "S",
      "ref": "*",
      "hyp": "ta"
     },
     {
      "eval_label": "S",
      "ref": "*",
      "hyp": "i"
     },
     {
      "eval_label": "S",
      "ref": "*",
      "hyp": "as"
     },
     {
      "eval_label": "S",
      "ref": "*",
      "hyp": "sekas"
     },
     {
      "eval_label": "S",
      "ref": "*s",
      "hyp": "rn"
     },
     {
      "eval_label": "S",
      "ref": "kleuren",
      "hyp": "fot"
     },
     {
      "eval_label": "S",
      "ref": "voetbal",
      "hyp": "pal"
     },
     {
      "eval_label": "S",
      "ref": "vlinder",
      "hyp": "lindog"
     }
    ]
   }
  }
 }
}