{
 "system_name": "hyp1",
 "speakers": {
  "S07C048V8_1LG": {
   "(S07C048V8_1LG-words)": {
    "SystemName": "hyp1",
    "SpeakerID": "S07C048V8_1LG",
    "sentence_id": "(S07C048V8_1LG-words)",
    "sequence": 0,
    "word_count": 42,
    "words": [
     {
      "eval_label": "C",
      "ref": "klas",
      "hyp": "klas"
     },
     {
      "eval_label": "C",
      "ref": "mooi",
      "hyp": "mooi"
     },
     {
      "eval_label": "S",
      "ref": "koe",
      "hyp": "ko"
     },
     {
      "eval_label": "C",
      "ref": "arm",
      "hyp": "arm"
     },
     {
      "eval_label": "C",
      "ref": "groei",
      "hyp": "groei"
     },
     {
      "eval_label": "C",
      "ref": "strand",
      "hyp": "strand"
     },
     {
      "eval_label": "S",
      "ref": "bed",
      "hyp": "bet"
     },
     {
      "eval_label": "S",
      "ref": "eerst*(eerste)",
      "hyp": "eerste"
     },
     {
      "eval_label": "C",
      "ref": "voor",
      "hyp": "voor"
     },
     {
      "eval_label": "D",
      "ref": "draai",
      "hyp": ""
     },
     {
      "eval_label": "S",
      "ref": "sjaal",
      "hyp": "traai"
     },
     {
      "eval_label": "S",
      "ref": "*(saai)",
      "hyp": "ssa"
     },
     {
      "eval_label": "S",
      "ref": "herfst",
      "hyp": "geerfst"
     },
     {
      "eval_label": "C",
      "ref": "herfst",
      "hyp": "herfst"
     },
     {
      "eval_label": "C",
      "ref": "duur",
      "hyp": "duur"
     },
     {
      "eval_label": "C",
      "ref": "straat",
      "hyp": "straat"
     },
     {
      "eval_label": "S",
      "ref": "leeuw",
      "hyp": "le"
     },
     {
      "eval_label": "S",
      "ref": "clown",
      "hyp": "lou"
     },
     {
      "eval_label": "C",
      "ref": "hoek",
      "hyp": "hoek"
     },
     {
      "eval_label": "S",
      "ref": "krant",
      "hyp": "kand"
     },
     {
      "eval_label": "S",
      "ref": "hout",
      "hyp": "hat"
     },
     {
      "eval_label": "S",
      "ref": "vriend",
      "hyp": "vrin"
     },
     {
      "eval_label": "S",
      "ref": "gauw*(gaai)",
      "hyp": "gi"
     },
     {
      "eval_label": "S",
      "ref": "chips*(gips)",
      "hyp": "gip"
     },
     {
      "eval_label": "C",
      "ref": "groen",
      "hyp": "groen"
     },
     {
      "eval_label": "C",
      "ref": "feest",
      "hyp": "feest"
     },
     {
      "eval_label": "C",
      "ref": "reis",
      "hyp": "reis"
     },
     {
      "eval_label": "D",
      "ref": "jas",
      "hyp": ""
     },
     {
      "eval_label": "S",
      "ref": "huis",
      "hyp": "jashas"
     },
     {
      "eval_label": "S",
      "ref": "paard",
      "hyp": "purt"
     },
     {
      "eval_label": "C",
      "ref": "vijf",
      "hyp": "vijf"
     },
     {
      "eval_label": "C",
      "ref": "muts",
      "hyp": "muts"
     },
     {
      "eval_label": "C",
      "ref": "nieuw",
      "hyp": "nieuw"
     },
     {
      "eval_label": "C",
      "ref": "kind",
      "hyp": "kind"
     },
     {
      "eval_label": "C",
      "ref": "bang",
      "hyp": "bang"
     },
     {
      "eval_label": "S",
      "ref": "oog",
      "hyp": "ooch"
     },
     {
      "eval_label": "C",
      "ref": "zacht",
      "hyp": "zacht"
     },
     {
      "eval_label": "C",
      "ref": "schoen",
      "hyp": "schoen"
     },
     {
      "eval_label": "C",
      "ref": "plas",
      "hyp": "plas"
     },
     {
      "eval_label": "C",
      "ref": "neus",
      "hyp": "neus"
     },
     {
      "eval_label": "S",
      "ref": "knoop",
      "hyp": "knoep"
     },
     {
      "eval_label": "C",
      "ref": "plank",
      "hyp": "plank"
     }
    ]
   }
  }
 }
}