{
 "system_name": "hyp1",
 "speakers": {
  "S04C035M2_1LGPseudo": {
   "(S04C035M2_1LGPseudo-words)": {
    "SystemName": "hyp1",
    "SpeakerID": "S04C035M2_1LGPseudo",
    "sentence_id": "(S04C035M2_1LGPseudo-words)",
    "sequence": 0,
    "word_count": 67,
    "words": [
     {
      "eval_label": "S",
      "ref": "*",
      "hyp": "f"
     },
     {
      "eval_label": "S",
      "ref": "fook",
      "hyp": "vok"
     },
     {
      "eval_label": "S",
      "ref": "sooi",
      "hyp": "vooi"
     },
     {
      "eval_label": "S",
      "ref": "*",
      "hyp": "doe"
     },
     {
      "eval_label": "S",
      "ref": "dau",
      "hyp": "do"
     },
     {
      "eval_label": "C",
      "ref": "ant",
      "hyp": "ant"
     },
     {
      "eval_label": "C",
      "ref": "beeg",
      "hyp": "beeg"
     },
     {
      "eval_label": "D",
      "ref": "*",
      "hyp": ""
     },
     {
      "eval_label": "S",
      "ref": "*",
      "hyp": "ssprien"
     },
     {
      "eval_label": "S",
      "ref": "*",
      "hyp": "spa"
     },
     {
      "eval_label": "C",
      "ref": "sprunt",
      "hyp": "sprunt"
     },
     {
      "eval_label": "D",
      "ref": "hool",
      "hyp": ""
     },
     {
      "eval_label": "D",
      "ref": "*",
      "hyp": ""
     },
     {
      "eval_label": "S",
      "ref": "*",
      "hyp": "rooi"
     },
     {
      "eval_label": "S",
      "ref": "*",
      "hyp": "lach"
     },
     {
      "eval_label": "S",
      "ref": "larst",
      "hyp": "t"
     },
     {
      "eval_label": "S",
      "ref": "*",
      "hyp": "last"
     },
     {
      "eval_label": "C",
      "ref": "vout",
      "hyp": "vout"
     },
     {
      "eval_label": "D",
      "ref": "zwoei",
      "hyp": ""
     },
     {
      "eval_label": "D",
      "ref": "*",
      "hyp": ""
     },
     {
      "eval_label": "D",
      "ref": "fam",
      "hyp": ""
     },
     {
      "eval_label": "D",
      "ref": "rachts",
      "hyp": ""
     },
     {
      "eval_label": "D",
      "ref": "vaap",
      "hyp": ""
     },
     {
      "eval_label": "D",
      "ref": "*",
      "hyp": ""
     },
     {
      "eval_label": "D",
      "ref": "sprieuw",
      "hyp": ""
     },
     {
      "eval_label": "S",
      "ref": "*",
      "hyp": "moei"
     },
     {
      "eval_label": "S",
      "ref": "*",
      "hyp": "van"
     },
     {
      "eval_label": "S",
      "ref": "keng",
      "hyp": "rh"
     },
     {
      "eval_label": "S",
      "ref": "swoers",
      "hyp": "vap"
     },
     {
      "eval_label": "S",
      "ref": "doer",
      "hyp": "ssprie"
     },
     {
      "eval_label": "S",
      "ref": "*",
      "hyp": "ka"
     },
     {
      "eval_label": "S",
      "ref": "*",
      "hyp": "ken"
     },
     {
      "eval_label": "S",
      "ref": "*",
      "hyp": "sour"
     },
     {
      "eval_label": "S",
      "ref": "plirt",
      "hyp": "dour"
     },
     {
      "eval_label": "S",
      "ref": "jien",
      "hyp": "lir"
     },
     {
      "eval_label": "S",
      "ref": "*",
      "hyp": "riplirt"
     },
     {
      "eval_label": "S",
      "ref": "*",
      "hyp": "je"
     },
     {
      "eval_label": "S",
      "ref": "*",
      "hyp": "jint"
     },
     {
      "eval_label": "S",
      "ref": "blard",
      "hyp": "blart"
     },
     {
      "eval_label": "S",
      "ref": "guul",
      "hyp": "gun"
     },
     {
      "eval_label": "C",
      "ref": "hoekt",
      "hyp": "hoekt"
     },
     {
      "eval_label": "S",
      "ref": "neeuw*(nieuw)",
      "hyp": "nieuw"
     },
     {
      "eval_label": "S",
      "ref": "*(noord)",
      "hyp": "noort"
     },
     {
      "eval_label": "C",
      "ref": "noork",
      "hyp": "noork"
     },
     {
      "eval_label": "D",
      "ref": "vid*(vind)",
      "hyp": ""
     },
     {
      "eval_label": "D",
      "ref": "zans",
      "hyp": ""
     },
     {
      "eval_label": "D",
      "ref": "*",
      "hyp": ""
     },
     {
      "eval_label": "S",
      "ref": "*(jan)",
      "hyp": "vind"
     },
     {
      "eval_label": "S",
      "ref": "leum",
      "hyp": "jang"
     },
     {
      "eval_label": "S",
      "ref": "haans",
      "hyp": "surry"
     },
     {
      "eval_label": "S",
      "ref": "*",
      "hyp": "jan"
     },
     {
      "eval_label": "S",
      "ref": "spaai",
      "hyp": "lum"
     },
     {
      "eval_label": "S",
      "ref": "sjalt*(sjaal)",
      "hyp": "hans"
     },
     {
      "eval_label": "S",
      "ref": "*s",
      "hyp": "s"
     },
     {
      "eval_label": "S",
      "ref": "*",
      "hyp": "spay"
     },
     {
      "eval_label": "S",
      "ref": "*",
      "hyp": "cial"
     },
     {
      "eval_label": "S",
      "ref": "heik",
      "hyp": "hetk"
     },
     {
      "eval_label": "C",
      "ref": "sank",
      "hyp": "sank"
     },
     {
      "eval_label": "C",
      "ref": "roen",
      "hyp": "roen"
     },
     {
      "eval_label": "D",
      "ref": "frijk",
      "hyp": ""
     },
     {
      "eval_label": "S",
      "ref": "eem",
      "hyp": "vrijk"
     },
     {
      "eval_label": "S",
      "ref": "schard",
      "hyp": "één"
     },
     {
      "eval_label": "S",
      "ref": "grek",
      "hyp": "gart"
     },
     {
      "eval_label": "S",
      "ref": "dron",
      "hyp": "grik"
     },
     {
      "eval_label": "S",
      "ref": "snaaf",
      "hyp": "drom"
     },
     {
      "eval_label": "S",
      "ref": "*",
      "hyp": "snaf"
     },
     {
      "eval_label": "S",
      "ref": "stuid",
      "hyp": "sstuit"
     }
    ]
   }
  }
 }
}