{
 "system_name": "hyp1",
 "speakers": {
  "S07C042M8_3+4LGPseudo": {
   "(S07C042M8_3+4LGPseudo-words)": {
    "SystemName": "hyp1",
    "SpeakerID": "S07C042M8_3+4LGPseudo",
    "sentence_id": "(S07C042M8_3+4LGPseudo-words)",
    "sequence": 0,
    "word_count": 68,
    "words": [
     {
      "eval_label": "I",
      "ref": "",
      "hyp": "omdur"
     },
     {
      "eval_label": "I",
      "ref": "",
      "hyp": "to"
     },
     {
      "eval_label": "I",
      "ref": "",
      "hyp": "te"
     },
     {
      "eval_label": "I",
      "ref": "",
      "hyp": "onwejlen"
     },
     {
      "eval_label": "I",
      "ref": "",
      "hyp": "jat"
     },
     {
      "eval_label": "I",
      "ref": "",
      "hyp": "de"
     },
     {
      "eval_label": "I",
      "ref": "",
      "hyp": "stient"
     },
     {
      "eval_label": "I",
      "ref": "",
      "hyp": "nu"
     },
     {
      "eval_label": "I",
      "ref": "",
      "hyp": "tien"
     },
     {
      "eval_label": "I",
      "ref": "",
      "hyp": "toe"
     },
     {
      "eval_label": "I",
      "ref": "",
      "hyp": "das"
     },
     {
      "eval_label": "I",
      "ref": "",
      "hyp": "duiveltje"
     },
     {
      "eval_label": "I",
      "ref": "",
      "hyp": "juitoni"
     },
     {
      "eval_label": "I",
      "ref": "",
      "hyp": "gevuitdel"
     },
     {
      "eval_label": "I",
      "ref": "",
      "hyp": "ciduan"
     },
     {
      "eval_label": "I",
      "ref": "",
      "hyp": "sprikkr"
     },
     {
      "eval_label": "I",
      "ref": "",
      "hyp": "wacht"
     },
     {
      "eval_label": "I",
      "ref": "",
      "hyp": "deniek"
     },
     {
      "eval_label": "I",
      "ref": "",
      "hyp": "verpirik"
     },
     {
      "eval_label": "I",
      "ref": "",
      "hyp": "napereew"
     },
     {
      "eval_label": "I",
      "ref": "",
      "hyp": "monterun"
     },
     {
      "eval_label": "I",
      "ref": "",
      "hyp": "il"
     },
     {
      "eval_label": "I",
      "ref": "",
      "hyp": "daspen"
     },
     {
      "eval_label": "I",
      "ref": "",
      "hyp": "kroe"
     },
     {
      "eval_label": "I",
      "ref": "",
      "hyp": "klunker"
     },
     {
      "eval_label": "I",
      "ref": "",
      "hyp": "kabes"
     },
     {
      "eval_label": "S",
      "ref": "ometuif",
      "hyp": "dipen"
     },
     {
      "eval_label": "S",
      "ref": "*",
      "hyp": "verwaig"
     },
     {
      "eval_label": "S",
      "ref": "toejietsen",
      "hyp": "o"
     },
     {
      "eval_label": "S",
      "ref": "oonwijlen",
      "hyp": "bikil"
     },
     {
      "eval_label": "S",
      "ref": "jattesiet",
      "hyp": "van"
     },
     {
      "eval_label": "S",
      "ref": "nurudien",
      "hyp": "delig"
     },
     {
      "eval_label": "S",
      "ref": "stoenydaas",
      "hyp": "jalkrim"
     },
     {
      "eval_label": "S",
      "ref": "deuveltek",
      "hyp": "smo"
     },
     {
      "eval_label": "S",
      "ref": "juitonie",
      "hyp": "la"
     },
     {
      "eval_label": "S",
      "ref": "gevijdel",
      "hyp": "is"
     },
     {
      "eval_label": "S",
      "ref": "sidowaan",
      "hyp": "dat"
     },
     {
      "eval_label": "S",
      "ref": "spekkeraai",
      "hyp": "zek"
     },
     {
      "eval_label": "S",
      "ref": "wachteniek",
      "hyp": "vlae"
     },
     {
      "eval_label": "S",
      "ref": "verpierik",
      "hyp": "ko"
     },
     {
      "eval_label": "S",
      "ref": "nappegreeuw",
      "hyp": "naro"
     },
     {
      "eval_label": "S",
      "ref": "mantaroen",
      "hyp": "twel"
     },
     {
      "eval_label": "S",
      "ref": "schielendaspen",
      "hyp": "lgen"
     },
     {
      "eval_label": "S",
      "ref": "crobeklunker",
      "hyp": "metergrook"
     },
     {
      "eval_label": "S",
      "ref": "kabbestepen",
      "hyp": "kan"
     },
     {
      "eval_label": "S",
      "ref": "verwarig",
      "hyp": "de"
     },
     {
      "eval_label": "S",
      "ref": "ooiebiekje",
      "hyp": "groorsten"
     },
     {
      "eval_label": "S",
      "ref": "fandelig",
      "hyp": "onderniet"
     },
     {
      "eval_label": "S",
      "ref": "jalekrewen",
      "hyp": "soadie"
     },
     {
      "eval_label": "S",
      "ref": "smoralij",
      "hyp": "ziner"
     },
     {
      "eval_label": "S",
      "ref": "*x",
      "hyp": "bra"
     },
     {
      "eval_label": "S",
      "ref": "zeekvlachine",
      "hyp": "eresprangen"
     },
     {
      "eval_label": "S",
      "ref": "kanaroe",
      "hyp": "blotendus"
     },
     {
      "eval_label": "S",
      "ref": "toineetlijgen",
      "hyp": "gidoor"
     },
     {
      "eval_label": "S",
      "ref": "meitsegrok",
      "hyp": "helder"
     },
     {
      "eval_label": "S",
      "ref": "kantelogsten",
      "hyp": "dober"
     },
     {
      "eval_label": "S",
      "ref": "ondermind",
      "hyp": "mud"
     },
     {
      "eval_label": "S",
      "ref": "choporatie",
      "hyp": "bun"
     },
     {
      "eval_label": "S",
      "ref": "zennebral",
      "hyp": "dals"
     },
     {
      "eval_label": "S",
      "ref": "ijraspangen",
      "hyp": "gouden"
     },
     {
      "eval_label": "S",
      "ref": "blottenduuf",
      "hyp": "havenlid"
     },
     {
      "eval_label": "S",
      "ref": "girdofhaalder",
      "hyp": "verbrakken"
     },
     {
      "eval_label": "S",
      "ref": "tobbermoeit",
      "hyp": "tja"
     },
     {
      "eval_label": "S",
      "ref": "poentalschouden",
      "hyp": "ja"
     },
     {
      "eval_label": "S",
      "ref": "havedil",
      "hyp": "hau"
     },
     {
      "eval_label": "S",
      "ref": "verbrakkertje",
      "hyp": "jak"
     },
     {
      "eval_label": "S",
      "ref": "gerauwejaak",
      "hyp": "haden"
     },
     {
      "eval_label": "S",
      "ref": "hapeneren",
      "hyp": "rin"
     }
    ]
   }
  }
 }
}