{
 "system_name": "hyp1",
 "speakers": {
  "S01C034M2_1LGPseudo": {
   "(S01C034M2_1LGPseudo-words)": {
    "SystemName": "hyp1",
    "SpeakerID": "S01C034M2_1LGPseudo",
    "sentence_id": "(S01C034M2_1LGPseudo-words)",
    "sequence": 0,
    "word_count": 46,
    "words": [
     {
      "eval_label": "S",
      "ref": "fook",
      "hyp": "foork"
     },
     {
      "eval_label": "C",
      "ref": "sooi",
      "hyp": "sooi"
     },
     {
      "eval_label": "S",
      "ref": "dau",
      "hyp": "taal"
     },
     {
      "eval_label": "C",
      "ref": "ant",
      "hyp": "ant"
     },
     {
      "eval_label": "C",
      "ref": "beeg",
      "hyp": "beeg"
     },
     {
      "eval_label": "S",
      "ref": "*",
      "hyp": "sprut"
     },
     {
      "eval_label": "C",
      "ref": "sprunt",
      "hyp": "sprunt"
     },
     {
      "eval_label": "S",
      "ref": "hool",
      "hyp": "hoel"
     },
     {
      "eval_label": "C",
      "ref": "larst",
      "hyp": "larst"
     },
     {
      "eval_label": "D",
      "ref": "vout",
      "hyp": ""
     },
     {
      "eval_label": "S",
      "ref": "zwoei",
      "hyp": "faats"
     },
     {
      "eval_label": "S",
      "ref": "fam",
      "hyp": "soi"
     },
     {
      "eval_label": "S",
      "ref": "*",
      "hyp": "van"
     },
     {
      "eval_label": "S",
      "ref": "rachts",
      "hyp": "racht"
     },
     {
      "eval_label": "C",
      "ref": "vaap",
      "hyp": "vaap"
     },
     {
      "eval_label": "S",
      "ref": "sprieuw",
      "hyp": "spriel"
     },
     {
      "eval_label": "S",
      "ref": "keng",
      "hyp": "ken"
     },
     {
      "eval_label": "S",
      "ref": "swoers",
      "hyp": "sword"
     },
     {
      "eval_label": "S",
      "ref": "*",
      "hyp": "door"
     },
     {
      "eval_label": "S",
      "ref": "doer",
      "hyp": "door"
     },
     {
      "eval_label": "S",
      "ref": "plirt",
      "hyp": "licht"
     },
     {
      "eval_label": "S",
      "ref": "jien",
      "hyp": "en"
     },
     {
      "eval_label": "S",
      "ref": "blard",
      "hyp": "plaht"
     },
     {
      "eval_label": "S",
      "ref": "guul",
      "hyp": "nu"
     },
     {
      "eval_label": "C",
      "ref": "hoekt",
      "hyp": "hoekt"
     },
     {
      "eval_label": "D",
      "ref": "neeuw",
      "hyp": ""
     },
     {
      "eval_label": "D",
      "ref": "noork",
      "hyp": ""
     },
     {
      "eval_label": "D",
      "ref": "vid",
      "hyp": ""
     },
     {
      "eval_label": "S",
      "ref": "zans",
      "hyp": "neel"
     },
     {
      "eval_label": "S",
      "ref": "leum",
      "hyp": "noorvit"
     },
     {
      "eval_label": "S",
      "ref": "haans",
      "hyp": "zand"
     },
     {
      "eval_label": "S",
      "ref": "spaai",
      "hyp": "le"
     },
     {
      "eval_label": "S",
      "ref": "sjalt",
      "hyp": "haens"
     },
     {
      "eval_label": "S",
      "ref": "heik",
      "hyp": "spay"
     },
     {
      "eval_label": "S",
      "ref": "*",
      "hyp": "jalt"
     },
     {
      "eval_label": "S",
      "ref": "sank",
      "hyp": "hek"
     },
     {
      "eval_label": "S",
      "ref": "*",
      "hyp": "zank"
     },
     {
      "eval_label": "C",
      "ref": "roen",
      "hyp": "roen"
     },
     {
      "eval_label": "S",
      "ref": "frijk",
      "hyp": "trek"
     },
     {
      "eval_label": "S",
      "ref": "eem",
      "hyp": "em"
     },
     {
      "eval_label": "S",
      "ref": "schard",
      "hyp": "gart"
     },
     {
      "eval_label": "S",
      "ref": "grek*(gek)",
      "hyp": "gek"
     },
     {
      "eval_label": "C",
      "ref": "dron",
      "hyp": "dron"
     },
     {
      "eval_label": "S",
      "ref": "snaaf",
      "hyp": "snaf"
     },
     {
      "eval_label": "S",
      "ref": "*",
      "hyp": "s"
     },
     {
      "eval_label": "S",
      "ref": "stuid",
      "hyp": "duit"
     }
    ]
   }
  }
 }
}