{
 "system_name": "hyp1",
 "speakers": {
  "S05C016V4_2LG": {
   "(S05C016V4_2LG-words)": {
    "SystemName": "hyp1",
    "SpeakerID": "S05C016V4_2LG",
    "sentence_id": "(S05C016V4_2LG-words)",
    "sequence": 0,
    "word_count": 46,
    "words": [
     {
      "eval_label": "I",
      "ref": "",
      "hyp": "hoe"
     },
     {
      "eval_label": "I",
      "ref": "",
      "hyp": "gat"
     },
     {
      "eval_label": "I",
      "ref": "",
      "hyp": "dar"
     },
     {
      "eval_label": "S",
      "ref": "water",
      "hyp": "me"
     },
     {
      "eval_label": "S",
      "ref": "mevrouw",
      "hyp": "vrouw"
     },
     {
      "eval_label": "C",
      "ref": "drogen",
      "hyp": "drogen"
     },
     {
      "eval_label": "S",
      "ref": "winkel",
      "hyp": "vintel"
     },
     {
      "eval_label": "C",
      "ref": "auto",
      "hyp": "auto"
     },
     {
      "eval_label": "C",
      "ref": "schouders",
      "hyp": "schouders"
     },
     {
      "eval_label": "S",
      "ref": "verhaal",
      "hyp": "varen"
     },
     {
      "eval_label": "S",
      "ref": "koning",
      "hyp": "coning"
     },
     {
      "eval_label": "S",
      "ref": "moeilijk",
      "hyp": "moluk"
     },
     {
      "eval_label": "C",
      "ref": "speelplaats",
      "hyp": "speelplaats"
     },
     {
      "eval_label": "C",
      "ref": "drinken",
      "hyp": "drinken"
     },
     {
      "eval_label": "C",
      "ref": "hoofdpijn",
      "hyp": "hoofdpijn"
     },
     {
      "eval_label": "C",
      "ref": "regen",
      "hyp": "regen"
     },
     {
      "eval_label": "I",
      "ref": "",
      "hyp": "vliegder"
     },
     {
      "eval_label": "I",
      "ref": "",
      "hyp": "stopen"
     },
     {
      "eval_label": "I",
      "ref": "",
      "hyp": "opniw"
     },
     {
      "eval_label": "S",
      "ref": "vliegtuig",
      "hyp": "go"
     },
     {
      "eval_label": "S",
      "ref": "stoppen",
      "hyp": "en"
     },
     {
      "eval_label": "S",
      "ref": "opnieuw",
      "hyp": "sneew"
     },
     {
      "eval_label": "S",
      "ref": "gooien",
      "hyp": "en"
     },
     {
      "eval_label": "S",
      "ref": "sneeuwen",
      "hyp": "modar"
     },
     {
      "eval_label": "S",
      "ref": "moeder",
      "hyp": "hitje"
     },
     {
      "eval_label": "S",
      "ref": "liedje",
      "hyp": "malot"
     },
     {
      "eval_label": "S",
      "ref": "potlood",
      "hyp": "fiets"
     },
     {
      "eval_label": "S",
      "ref": "fietsbel",
      "hyp": "wel"
     },
     {
      "eval_label": "S",
      "ref": "vinger",
      "hyp": "vingja"
     },
     {
      "eval_label": "C",
      "ref": "dichtbij",
      "hyp": "dichtbij"
     },
     {
      "eval_label": "S",
      "ref": "meisje",
      "hyp": "mese"
     },
     {
      "eval_label": "S",
      "ref": "chauffeur",
      "hyp": "chafer"
     },
     {
      "eval_label": "S",
      "ref": "muziek",
      "hyp": "msiq"
     },
     {
      "eval_label": "S",
      "ref": "waarom",
      "hyp": "waron"
     },
     {
      "eval_label": "S",
      "ref": "scheuren",
      "hyp": "voren"
     },
     {
      "eval_label": "S",
      "ref": "lawaai",
      "hyp": "lai"
     },
     {
      "eval_label": "S",
      "ref": "zwemmen",
      "hyp": "semen"
     },
     {
      "eval_label": "C",
      "ref": "vuurwerk",
      "hyp": "vuurwerk"
     },
     {
      "eval_label": "S",
      "ref": "appel",
      "hyp": "apal"
     },
     {
      "eval_label": "C",
      "ref": "cola",
      "hyp": "cola"
     },
     {
      "eval_label": "S",
      "ref": "kussen",
      "hyp": "cusen"
     },
     {
      "eval_label": "S",
      "ref": "eerste",
      "hyp": "eerte"
     },
     {
      "eval_label": "S",
      "ref": "circus",
      "hyp": "sertus"
     },
     {
      "eval_label": "S",
      "ref": "kleuren",
      "hyp": "klora"
     },
     {
      "eval_label": "S",
      "ref": "voetbal",
      "hyp": "voorwel"
     },
     {
      "eval_label": "S",
      "ref": "vlinder*(vinger)",
      "hyp": "wijnar"
     }
    ]
   }
  }
 }
}