{
 "system_name": "hyp1",
 "speakers": {
  "S04C033V2_2LGPseudo": {
   "(S04C033V2_2LGPseudo-words)": {
    "SystemName": "hyp1",
    "SpeakerID": "S04C033V2_2LGPseudo",
    "sentence_id": "(S04C033V2_2LGPseudo-words)",
    "sequence": 0,
    "word_count": 52,
    "words": [
     {
      "eval_label": "S",
      "ref": "millen",
      "hyp": "menen"
     },
     {
      "eval_label": "S",
      "ref": "vocil",
      "hyp": "vokil"
     },
     {
      "eval_label": "C",
      "ref": "geutel",
      "hyp": "geutel"
     },
     {
      "eval_label": "I",
      "ref": "",
      "hyp": "shobbel"
     },
     {
      "eval_label": "S",
      "ref": "sjobel",
      "hyp": "ir"
     },
     {
      "eval_label": "S",
      "ref": "ierpieuw",
      "hyp": "pio"
     },
     {
      "eval_label": "S",
      "ref": "walaan",
      "hyp": "wolaan"
     },
     {
      "eval_label": "C",
      "ref": "erke",
      "hyp": "erke"
     },
     {
      "eval_label": "S",
      "ref": "*",
      "hyp": "hawa"
     },
     {
      "eval_label": "C",
      "ref": "haweel",
      "hyp": "haweel"
     },
     {
      "eval_label": "S",
      "ref": "saarweng",
      "hyp": "sarwing"
     },
     {
      "eval_label": "C",
      "ref": "gevicht",
      "hyp": "gevicht"
     },
     {
      "eval_label": "S",
      "ref": "eemde",
      "hyp": "inde"
     },
     {
      "eval_label": "S",
      "ref": "*",
      "hyp": "bebea"
     },
     {
      "eval_label": "S",
      "ref": "*",
      "hyp": "bebuikbebaat"
     },
     {
      "eval_label": "S",
      "ref": "bepoud",
      "hyp": "os"
     },
     {
      "eval_label": "S",
      "ref": "*",
      "hyp": "tou"
     },
     {
      "eval_label": "S",
      "ref": "*",
      "hyp": "k"
     },
     {
      "eval_label": "S",
      "ref": "orstalk",
      "hyp": "oostouk"
     },
     {
      "eval_label": "S",
      "ref": "veten*(vetten)",
      "hyp": "vitten"
     },
     {
      "eval_label": "S",
      "ref": "*",
      "hyp": "gift"
     },
     {
      "eval_label": "S",
      "ref": "*",
      "hyp": "oul"
     },
     {
      "eval_label": "S",
      "ref": "gefouw",
      "hyp": "gefal"
     },
     {
      "eval_label": "S",
      "ref": "vurpaand",
      "hyp": "vurband"
     },
     {
      "eval_label": "S",
      "ref": "nizung",
      "hyp": "mizoun"
     },
     {
      "eval_label": "S",
      "ref": "fiewon",
      "hyp": "fil"
     },
     {
      "eval_label": "S",
      "ref": "*",
      "hyp": "o"
     },
     {
      "eval_label": "S",
      "ref": "*",
      "hyp": "viv"
     },
     {
      "eval_label": "S",
      "ref": "kneurem",
      "hyp": "kneuren"
     },
     {
      "eval_label": "S",
      "ref": "vawaai",
      "hyp": "vawi"
     },
     {
      "eval_label": "S",
      "ref": "strellen",
      "hyp": "sterlen"
     },
     {
      "eval_label": "C",
      "ref": "zwieten",
      "hyp": "zwieten"
     },
     {
      "eval_label": "S",
      "ref": "foetbans",
      "hyp": "voetbanners"
     },
     {
      "eval_label": "S",
      "ref": "oonste",
      "hyp": "onerste"
     },
     {
      "eval_label": "S",
      "ref": "muider",
      "hyp": "muide"
     },
     {
      "eval_label": "S",
      "ref": "grijnken",
      "hyp": "grenken"
     },
     {
      "eval_label": "S",
      "ref": "schielstaug",
      "hyp": "schiostar"
     },
     {
      "eval_label": "S",
      "ref": "prilsood",
      "hyp": "prilsoot"
     },
     {
      "eval_label": "S",
      "ref": "vloender",
      "hyp": "vlouender"
     },
     {
      "eval_label": "S",
      "ref": "milste",
      "hyp": "leoster"
     },
     {
      "eval_label": "C",
      "ref": "veurder",
      "hyp": "veurder"
     },
     {
      "eval_label": "S",
      "ref": "kloeien",
      "hyp": "clouen"
     },
     {
      "eval_label": "C",
      "ref": "ulen",
      "hyp": "ulen"
     },
     {
      "eval_label": "C",
      "ref": "orponk",
      "hyp": "orponk"
     },
     {
      "eval_label": "D",
      "ref": "*",
      "hyp": ""
     },
     {
      "eval_label": "C",
      "ref": "schodig",
      "hyp": "schodig"
     },
     {
      "eval_label": "S",
      "ref": "ijpo",
      "hyp": "epol"
     },
     {
      "eval_label": "C",
      "ref": "menuur",
      "hyp": "menuur"
     },
     {
      "eval_label": "I",
      "ref": "",
      "hyp": "spreik"
     },
     {
      "eval_label": "S",
      "ref": "spreikje",
      "hyp": "je"
     },
     {
      "eval_label": "S",
      "ref": "hiffreeuw",
      "hyp": "hifreew"
     },
     {
      "eval_label": "C",
      "ref": "wooien",
      "hyp": "wooien"
     }
    ]
   }
  }
 }
}